README
setup.py
django_versionedcache.egg-info/PKG-INFO
django_versionedcache.egg-info/SOURCES.txt
django_versionedcache.egg-info/dependency_links.txt
django_versionedcache.egg-info/requires.txt
django_versionedcache.egg-info/top_level.txt
versionedcache/__init__.py
versionedcache/backend.py
versionedcache/debug.py
versionedcache/middleware.py