Metadata-Version: 1.0
Name: django-versionedcache
Version: 0.1.2
Summary: django versioned cache
Home-page: UNKNOWN
Author: centrum holdings s.r.o
Author-email: UNKNOWN
License: BSD
Platform: UNKNOWN
